mylightsystems/.gitkeep
mylightsystems/__init__.py
mylightsystems/client.py
mylightsystems/const.py
mylightsystems/device_factory.py
mylightsystems/exceptions.py
mylightsystems/models.py
mylightsystems/py.typed
mylightsystems-0.0.9.dist-info/METADATA
mylightsystems-0.0.9.dist-info/WHEEL
mylightsystems-0.0.9.dist-info/RECORD
