Metadata-Version: 2.3
Name: mylightsystems
Version: 0.0.9
Summary: Asynchronous Python client for MyLight Systems.
License: MIT
Keywords: MyLight Systems,api,async,client
Author: Pierre-Emmanuel Mercier
Author-email: acesyde@gmail.com
Maintainer: Pierre-Emmanuel Mercier
Maintainer-email: acesyde@gmail.com
Requires-Python: >=3.13
Classifier: Development Status :: 5 - Production/Stable
Classifier: Framework :: AsyncIO
Classifier: Intended Audience :: Developers
Classifier: Natural Language :: English
Classifier: Programming Language :: Python :: 3.11
Classifier: Programming Language :: Python :: 3.12
Classifier: Programming Language :: Python :: 3.13
Classifier: Programming Language :: Python :: 3
Classifier: Topic :: Software Development :: Libraries :: Python Modules
Requires-Dist: aiohttp (>=3.0.0,<4.0.0)
Requires-Dist: mashumaro (>=3.11,<4.0.0)
Requires-Dist: orjson (>=3.9.0,<4.0.0)
Requires-Dist: yarl (>=1.6.0,<2.0.0)
Project-URL: Bug Tracker, https://github.com/acesyde/python-mylight-systems-api-client/issues
Project-URL: Changelog, https://github.com/acesyde/python-mylight-systems-api-client/releases
Project-URL: Documentation, https://github.com/acesyde/python-mylight-systems-api-client
Project-URL: Homepage, https://github.com/acesyde/python-mylight-systems-api-client
Project-URL: Repository, https://github.com/acesyde/python-mylight-systems-api-client
